{
  "alias": "aps",
  "prefix": "java",
  "suffix": null,
  "suggestions": [
    {
      "suggType": "KeywordSuggestion",
      "type": "KEYWORD",
      "value": "java sok",
      "refTag": "nb_sb_ss_i_1_4",
      "ghost": false,
      "help": false,
      "queryUnderstandingFeatures": [
        { "source": "QU_TOOL", "annotations": [] }
      ],
      "xcatOnly": false,
      "fallback": false,
      "blackListed": false,
      "spellCorrected": false
    },
    {
      "suggType": "KeywordSuggestion",
      "type": "KEYWORD",
      "value": "javascript",
      "refTag": "nb_sb_ss_i_3_4",
      "ghost": false,
      "help": false,
      "queryUnderstandingFeatures": [
        { "source": "QU_TOOL", "annotations": [] }
      ],
      "xcatOnly": false,
      "fallback": false,
      "blackListed": false,
      "spellCorrected": false
    },
    {
      "suggType": "KeywordSuggestion",
      "type": "KEYWORD",
      "value": "java moss",
      "refTag": "nb_sb_ss_i_4_4",
      "ghost": false,
      "help": false,
      "queryUnderstandingFeatures": [
        { "source": "QU_TOOL", "annotations": [] }
      ],
      "xcatOnly": false,
      "fallback": false,
      "blackListed": false,
      "spellCorrected": false
    },
    {
      "suggType": "KeywordSuggestion",
      "type": "KEYWORD",
      "value": "java house cold brew coffee liquid pods",
      "refTag": "nb_sb_ss_i_5_4",
      "ghost": false,
      "help": false,
      "queryUnderstandingFeatures": [
        { "source": "QU_TOOL", "annotations": [] }
      ],
      "xcatOnly": false,
      "fallback": false,
      "blackListed": false,
      "spellCorrected": false
    },
    {
      "suggType": "KeywordSuggestion",
      "type": "KEYWORD",
      "value": "java gel stain",
      "refTag": "nb_sb_ss_i_6_4",
      "ghost": false,
      "help": false,
      "queryUnderstandingFeatures": [
        { "source": "QU_TOOL", "annotations": [] }
      ],
      "xcatOnly": false,
      "fallback": false,
      "blackListed": false,
      "spellCorrected": false
    },
    {
      "suggType": "KeywordSuggestion",
      "type": "KEYWORD",
      "value": "java",
      "refTag": "nb_sb_ss_i_7_4",
      "ghost": false,
      "help": false,
      "queryUnderstandingFeatures": [
        { "source": "QU_TOOL", "annotations": [] }
      ],
      "xcatOnly": false,
      "fallback": false,
      "blackListed": false,
      "spellCorrected": false
    },
    {
      "suggType": "KeywordSuggestion",
      "type": "KEYWORD",
      "value": "java monster",
      "refTag": "nb_sb_ss_i_8_4",
      "ghost": false,
      "help": false,
      "queryUnderstandingFeatures": [
        { "source": "QU_TOOL", "annotations": [] }
      ],
      "xcatOnly": false,
      "fallback": false,
      "blackListed": false,
      "spellCorrected": false
    },
    {
      "suggType": "KeywordSuggestion",
      "type": "KEYWORD",
      "value": "java fern",
      "refTag": "nb_sb_ss_i_9_4",
      "ghost": false,
      "help": false,
      "queryUnderstandingFeatures": [
        { "source": "QU_TOOL", "annotations": [] }
      ],
      "xcatOnly": false,
      "fallback": false,
      "blackListed": false,
      "spellCorrected": false
    },
    {
      "suggType": "KeywordSuggestion",
      "type": "KEYWORD",
      "value": "java sok 32 oz",
      "refTag": "nb_sb_ss_i_10_4",
      "ghost": false,
      "help": false,
      "queryUnderstandingFeatures": [
        { "source": "QU_TOOL", "annotations": [] }
      ],
      "xcatOnly": false,
      "fallback": false,
      "blackListed": false,
      "spellCorrected": false
    },
    {
      "suggType": "KeywordSuggestion",
      "type": "KEYWORD",
      "value": "javapresse manual coffee grinder, conical burr mill",
      "refTag": "nb_sb_ss_i_11_4",
      "ghost": false,
      "help": false,
      "queryUnderstandingFeatures": [
        { "source": "QU_TOOL", "annotations": [] }
      ],
      "xcatOnly": false,
      "fallback": false,
      "blackListed": false,
      "spellCorrected": false
    }
  ],
  "responseId": "2OLSHPRQMAL9",
  "shuffled": false
}
